{"msg":"All Slice Page Data","data":[{"image_slice_id":13880,"image_slice_original_path":"http:\/\/quran.kemenag.go.id\/api\/source\/slice\/4\/4_01.jpg","image_slice_original_width":1350,"image_slice_original_height":187,"image_slice_large_path":"","image_slice_large_width":0,"image_slice_large_height":0,"image_slice_medium_path":"","image_slice_medium_width":0,"image_slice_medium_height":0,"image_slice_small_path":"","image_slice_small_width":0,"image_slice_small_height":0,"image_slice_thumbnail_path":"","image_slice_thumbnail_width":0,"image_slice_thumbnail_height":0,"aya_id":null,"image_slice_index":1,"page_id":334},{"image_slice_id":13881,"image_slice_original_path":"http:\/\/quran.kemenag.go.id\/api\/source\/slice\/4\/4_02.jpg","image_slice_original_width":176,"image_slice_original_height":89,"image_slice_large_path":"","image_slice_large_width":0,"image_slice_large_height":0,"image_slice_medium_path":"","image_slice_medium_width":0,"image_slice_medium_height":0,"image_slice_small_path":"","image_slice_small_width":0,"image_slice_small_height":0,"image_slice_thumbnail_path":"","image_slice_thumbnail_width":0,"image_slice_thumbnail_height":0,"aya_id":null,"image_slice_index":2,"page_id":334},{"image_slice_id":13882,"image_slice_original_path":"http:\/\/quran.kemenag.go.id\/api\/source\/slice\/4\/4_03.jpg","image_slice_original_width":999,"image_slice_original_height":89,"image_slice_large_path":"","image_slice_large_width":0,"image_slice_large_height":0,"image_slice_medium_path":"","image_slice_medium_width":0,"image_slice_medium_height":0,"image_slice_small_path":"","image_slice_small_width":0,"image_slice_small_height":0,"image_slice_thumbnail_path":"","image_slice_thumbnail_width":0,"image_slice_thumbnail_height":0,"aya_id":24,"image_slice_index":3,"page_id":334},{"image_slice_id":13883,"image_slice_original_path":"http:\/\/quran.kemenag.go.id\/api\/source\/slice\/4\/4_04.jpg","image_slice_original_width":175,"image_slice_original_height":89,"image_slice_large_path":"","image_slice_large_width":0,"image_slice_large_height":0,"image_slice_medium_path":"","image_slice_medium_width":0,"image_slice_medium_height":0,"image_slice_small_path":"","image_slice_small_width":0,"image_slice_small_height":0,"image_slice_thumbnail_path":"","image_slice_thumbnail_width":0,"image_slice_thumbnail_height":0,"aya_id":null,"image_slice_index":4,"page_id":334},{"image_slice_id":13884,"image_slice_original_path":"http:\/\/quran.kemenag.go.id\/api\/source\/slice\/4\/4_05.jpg","image_slice_original_width":176,"image_slice_original_height":100,"image_slice_large_path":"","image_slice_large_width":0,"image_slice_large_height":0,"image_slice_medium_path":"","image_slice_medium_width":0,"image_slice_medium_height":0,"image_slice_small_path":"","image_slice_small_width":0,"image_slice_small_height":0,"image_slice_thumbnail_path":"","image_slice_thumbnail_width":0,"image_slice_thumbnail_height":0,"aya_id":null,"image_slice_index":5,"page_id":334},{"image_slice_id":13885,"image_slice_original_path":"http:\/\/quran.kemenag.go.id\/api\/source\/slice\/4\/4_06.jpg","image_slice_original_width":84,"image_slice_original_height":100,"image_slice_large_path":"","image_slice_large_width":0,"image_slice_large_height":0,"image_slice_medium_path":"","image_slice_medium_width":0,"image_slice_medium_height":0,"image_slice_small_path":"","image_slice_small_width":0,"image_slice_small_height":0,"image_slice_thumbnail_path":"","image_slice_thumbnail_width":0,"image_slice_thumbnail_height":0,"aya_id":25,"image_slice_index":6,"page_id":334},{"image_slice_id":13886,"image_slice_original_path":"http:\/\/quran.kemenag.go.id\/api\/source\/slice\/4\/4_07.jpg","image_slice_original_width":915,"image_slice_original_height":100,"image_slice_large_path":"","image_slice_large_width":0,"image_slice_large_height":0,"image_slice_medium_path":"","image_slice_medium_width":0,"image_slice_medium_height":0,"image_slice_small_path":"","image_slice_small_width":0,"image_slice_small_height":0,"image_slice_thumbnail_path":"","image_slice_thumbnail_width":0,"image_slice_thumbnail_height":0,"aya_id":24,"image_slice_index":7,"page_id":334},{"image_slice_id":13887,"image_slice_original_path":"http:\/\/quran.kemenag.go.id\/api\/source\/slice\/4\/4_08.jpg","image_slice_original_width":175,"image_slice_original_height":100,"image_slice_large_path":"","image_slice_large_width":0,"image_slice_large_height":0,"image_slice_medium_path":"","image_slice_medium_width":0,"image_slice_medium_height":0,"image_slice_small_path":"","image_slice_small_width":0,"image_slice_small_height":0,"image_slice_thumbnail_path":"","image_slice_thumbnail_width":0,"image_slice_thumbnail_height":0,"aya_id":null,"image_slice_index":8,"page_id":334},{"image_slice_id":13888,"image_slice_original_path":"http:\/\/quran.kemenag.go.id\/api\/source\/slice\/4\/4_09.jpg","image_slice_original_width":176,"image_slice_original_height":113,"image_slice_large_path":"","image_slice_large_width":0,"image_slice_large_height":0,"image_slice_medium_path":"","image_slice_medium_width":0,"image_slice_medium_height":0,"image_slice_small_path":"","image_slice_small_width":0,"image_slice_small_height":0,"image_slice_thumbnail_path":"","image_slice_thumbnail_width":0,"image_slice_thumbnail_height":0,"aya_id":null,"image_slice_index":9,"page_id":334},{"image_slice_id":13889,"image_slice_original_path":"http:\/\/quran.kemenag.go.id\/api\/source\/slice\/4\/4_10.jpg","image_slice_original_width":481,"image_slice_original_height":113,"image_slice_large_path":"","image_slice_large_width":0,"image_slice_large_height":0,"image_slice_medium_path":"","image_slice_medium_width":0,"image_slice_medium_height":0,"image_slice_small_path":"","image_slice_small_width":0,"image_slice_small_height":0,"image_slice_thumbnail_path":"","image_slice_thumbnail_width":0,"image_slice_thumbnail_height":0,"aya_id":26,"image_slice_index":10,"page_id":334},{"image_slice_id":13890,"image_slice_original_path":"http:\/\/quran.kemenag.go.id\/api\/source\/slice\/4\/4_11.jpg","image_slice_original_width":518,"image_slice_original_height":113,"image_slice_large_path":"","image_slice_large_width":0,"image_slice_large_height":0,"image_slice_medium_path":"","image_slice_medium_width":0,"image_slice_medium_height":0,"image_slice_small_path":"","image_slice_small_width":0,"image_slice_small_height":0,"image_slice_thumbnail_path":"","image_slice_thumbnail_width":0,"image_slice_thumbnail_height":0,"aya_id":25,"image_slice_index":11,"page_id":334},{"image_slice_id":13891,"image_slice_original_path":"http:\/\/quran.kemenag.go.id\/api\/source\/slice\/4\/4_12.jpg","image_slice_original_width":175,"image_slice_original_height":113,"image_slice_large_path":"","image_slice_large_width":0,"image_slice_large_height":0,"image_slice_medium_path":"","image_slice_medium_width":0,"image_slice_medium_height":0,"image_slice_small_path":"","image_slice_small_width":0,"image_slice_small_height":0,"image_slice_thumbnail_path":"","image_slice_thumbnail_width":0,"image_slice_thumbnail_height":0,"aya_id":null,"image_slice_index":12,"page_id":334},{"image_slice_id":13892,"image_slice_original_path":"http:\/\/quran.kemenag.go.id\/api\/source\/slice\/4\/4_13.jpg","image_slice_original_width":176,"image_slice_original_height":100,"image_slice_large_path":"","image_slice_large_width":0,"image_slice_large_height":0,"image_slice_medium_path":"","image_slice_medium_width":0,"image_slice_medium_height":0,"image_slice_small_path":"","image_slice_small_width":0,"image_slice_small_height":0,"image_slice_thumbnail_path":"","image_slice_thumbnail_width":0,"image_slice_thumbnail_height":0,"aya_id":null,"image_slice_index":13,"page_id":334},{"image_slice_id":13893,"image_slice_original_path":"http:\/\/quran.kemenag.go.id\/api\/source\/slice\/4\/4_14.jpg","image_slice_original_width":999,"image_slice_original_height":100,"image_slice_large_path":"","image_slice_large_width":0,"image_slice_large_height":0,"image_slice_medium_path":"","image_slice_medium_width":0,"image_slice_medium_height":0,"image_slice_small_path":"","image_slice_small_width":0,"image_slice_small_height":0,"image_slice_thumbnail_path":"","image_slice_thumbnail_width":0,"image_slice_thumbnail_height":0,"aya_id":26,"image_slice_index":14,"page_id":334},{"image_slice_id":13894,"image_slice_original_path":"http:\/\/quran.kemenag.go.id\/api\/source\/slice\/4\/4_15.jpg","image_slice_original_width":175,"image_slice_original_height":100,"image_slice_large_path":"","image_slice_large_width":0,"image_slice_large_height":0,"image_slice_medium_path":"","image_slice_medium_width":0,"image_slice_medium_height":0,"image_slice_small_path":"","image_slice_small_width":0,"image_slice_small_height":0,"image_slice_thumbnail_path":"","image_slice_thumbnail_width":0,"image_slice_thumbnail_height":0,"aya_id":null,"image_slice_index":15,"page_id":334},{"image_slice_id":13895,"image_slice_original_path":"http:\/\/quran.kemenag.go.id\/api\/source\/slice\/4\/4_16.jpg","image_slice_original_width":176,"image_slice_original_height":92,"image_slice_large_path":"","image_slice_large_width":0,"image_slice_large_height":0,"image_slice_medium_path":"","image_slice_medium_width":0,"image_slice_medium_height":0,"image_slice_small_path":"","image_slice_small_width":0,"image_slice_small_height":0,"image_slice_thumbnail_path":"","image_slice_thumbnail_width":0,"image_slice_thumbnail_height":0,"aya_id":null,"image_slice_index":16,"page_id":334},{"image_slice_id":13896,"image_slice_original_path":"http:\/\/quran.kemenag.go.id\/api\/source\/slice\/4\/4_17.jpg","image_slice_original_width":307,"image_slice_original_height":92,"image_slice_large_path":"","image_slice_large_width":0,"image_slice_large_height":0,"image_slice_medium_path":"","image_slice_medium_width":0,"image_slice_medium_height":0,"image_slice_small_path":"","image_slice_small_width":0,"image_slice_small_height":0,"image_slice_thumbnail_path":"","image_slice_thumbnail_width":0,"image_slice_thumbnail_height":0,"aya_id":27,"image_slice_index":17,"page_id":334},{"image_slice_id":13897,"image_slice_original_path":"http:\/\/quran.kemenag.go.id\/api\/source\/slice\/4\/4_18.jpg","image_slice_original_width":692,"image_slice_original_height":92,"image_slice_large_path":"","image_slice_large_width":0,"image_slice_large_height":0,"image_slice_medium_path":"","image_slice_medium_width":0,"image_slice_medium_height":0,"image_slice_small_path":"","image_slice_small_width":0,"image_slice_small_height":0,"image_slice_thumbnail_path":"","image_slice_thumbnail_width":0,"image_slice_thumbnail_height":0,"aya_id":26,"image_slice_index":18,"page_id":334},{"image_slice_id":13898,"image_slice_original_path":"http:\/\/quran.kemenag.go.id\/api\/source\/slice\/4\/4_19.jpg","image_slice_original_width":175,"image_slice_original_height":92,"image_slice_large_path":"","image_slice_large_width":0,"image_slice_large_height":0,"image_slice_medium_path":"","image_slice_medium_width":0,"image_slice_medium_height":0,"image_slice_small_path":"","image_slice_small_width":0,"image_slice_small_height":0,"image_slice_thumbnail_path":"","image_slice_thumbnail_width":0,"image_slice_thumbnail_height":0,"aya_id":null,"image_slice_index":19,"page_id":334},{"image_slice_id":13899,"image_slice_original_path":"http:\/\/quran.kemenag.go.id\/api\/source\/slice\/4\/4_20.jpg","image_slice_original_width":176,"image_slice_original_height":211,"image_slice_large_path":"","image_slice_large_width":0,"image_slice_large_height":0,"image_slice_medium_path":"","image_slice_medium_width":0,"image_slice_medium_height":0,"image_slice_small_path":"","image_slice_small_width":0,"image_slice_small_height":0,"image_slice_thumbnail_path":"","image_slice_thumbnail_width":0,"image_slice_thumbnail_height":0,"aya_id":null,"image_slice_index":20,"page_id":334},{"image_slice_id":13900,"image_slice_original_path":"http:\/\/quran.kemenag.go.id\/api\/source\/slice\/4\/4_21.jpg","image_slice_original_width":999,"image_slice_original_height":211,"image_slice_large_path":"","image_slice_large_width":0,"image_slice_large_height":0,"image_slice_medium_path":"","image_slice_medium_width":0,"image_slice_medium_height":0,"image_slice_small_path":"","image_slice_small_width":0,"image_slice_small_height":0,"image_slice_thumbnail_path":"","image_slice_thumbnail_width":0,"image_slice_thumbnail_height":0,"aya_id":27,"image_slice_index":21,"page_id":334},{"image_slice_id":13901,"image_slice_original_path":"http:\/\/quran.kemenag.go.id\/api\/source\/slice\/4\/4_22.jpg","image_slice_original_width":175,"image_slice_original_height":211,"image_slice_large_path":"","image_slice_large_width":0,"image_slice_large_height":0,"image_slice_medium_path":"","image_slice_medium_width":0,"image_slice_medium_height":0,"image_slice_small_path":"","image_slice_small_width":0,"image_slice_small_height":0,"image_slice_thumbnail_path":"","image_slice_thumbnail_width":0,"image_slice_thumbnail_height":0,"aya_id":null,"image_slice_index":22,"page_id":334},{"image_slice_id":13902,"image_slice_original_path":"http:\/\/quran.kemenag.go.id\/api\/source\/slice\/4\/4_23.jpg","image_slice_original_width":176,"image_slice_original_height":95,"image_slice_large_path":"","image_slice_large_width":0,"image_slice_large_height":0,"image_slice_medium_path":"","image_slice_medium_width":0,"image_slice_medium_height":0,"image_slice_small_path":"","image_slice_small_width":0,"image_slice_small_height":0,"image_slice_thumbnail_path":"","image_slice_thumbnail_width":0,"image_slice_thumbnail_height":0,"aya_id":null,"image_slice_index":23,"page_id":334},{"image_slice_id":13903,"image_slice_original_path":"http:\/\/quran.kemenag.go.id\/api\/source\/slice\/4\/4_24.jpg","image_slice_original_width":739,"image_slice_original_height":95,"image_slice_large_path":"","image_slice_large_width":0,"image_slice_large_height":0,"image_slice_medium_path":"","image_slice_medium_width":0,"image_slice_medium_height":0,"image_slice_small_path":"","image_slice_small_width":0,"image_slice_small_height":0,"image_slice_thumbnail_path":"","image_slice_thumbnail_width":0,"image_slice_thumbnail_height":0,"aya_id":28,"image_slice_index":24,"page_id":334},{"image_slice_id":13904,"image_slice_original_path":"http:\/\/quran.kemenag.go.id\/api\/source\/slice\/4\/4_25.jpg","image_slice_original_width":260,"image_slice_original_height":95,"image_slice_large_path":"","image_slice_large_width":0,"image_slice_large_height":0,"image_slice_medium_path":"","image_slice_medium_width":0,"image_slice_medium_height":0,"image_slice_small_path":"","image_slice_small_width":0,"image_slice_small_height":0,"image_slice_thumbnail_path":"","image_slice_thumbnail_width":0,"image_slice_thumbnail_height":0,"aya_id":27,"image_slice_index":25,"page_id":334},{"image_slice_id":13905,"image_slice_original_path":"http:\/\/quran.kemenag.go.id\/api\/source\/slice\/4\/4_26.jpg","image_slice_original_width":175,"image_slice_original_height":95,"image_slice_large_path":"","image_slice_large_width":0,"image_slice_large_height":0,"image_slice_medium_path":"","image_slice_medium_width":0,"image_slice_medium_height":0,"image_slice_small_path":"","image_slice_small_width":0,"image_slice_small_height":0,"image_slice_thumbnail_path":"","image_slice_thumbnail_width":0,"image_slice_thumbnail_height":0,"aya_id":null,"image_slice_index":26,"page_id":334},{"image_slice_id":13906,"image_slice_original_path":"http:\/\/quran.kemenag.go.id\/api\/source\/slice\/4\/4_27.jpg","image_slice_original_width":176,"image_slice_original_height":100,"image_slice_large_path":"","image_slice_large_width":0,"image_slice_large_height":0,"image_slice_medium_path":"","image_slice_medium_width":0,"image_slice_medium_height":0,"image_slice_small_path":"","image_slice_small_width":0,"image_slice_small_height":0,"image_slice_thumbnail_path":"","image_slice_thumbnail_width":0,"image_slice_thumbnail_height":0,"aya_id":null,"image_slice_index":27,"page_id":334},{"image_slice_id":13907,"image_slice_original_path":"http:\/\/quran.kemenag.go.id\/api\/source\/slice\/4\/4_28.jpg","image_slice_original_width":292,"image_slice_original_height":100,"image_slice_large_path":"","image_slice_large_width":0,"image_slice_large_height":0,"image_slice_medium_path":"","image_slice_medium_width":0,"image_slice_medium_height":0,"image_slice_small_path":"","image_slice_small_width":0,"image_slice_small_height":0,"image_slice_thumbnail_path":"","image_slice_thumbnail_width":0,"image_slice_thumbnail_height":0,"aya_id":29,"image_slice_index":28,"page_id":334},{"image_slice_id":13908,"image_slice_original_path":"http:\/\/quran.kemenag.go.id\/api\/source\/slice\/4\/4_29.jpg","image_slice_original_width":707,"image_slice_original_height":100,"image_slice_large_path":"","image_slice_large_width":0,"image_slice_large_height":0,"image_slice_medium_path":"","image_slice_medium_width":0,"image_slice_medium_height":0,"image_slice_small_path":"","image_slice_small_width":0,"image_slice_small_height":0,"image_slice_thumbnail_path":"","image_slice_thumbnail_width":0,"image_slice_thumbnail_height":0,"aya_id":28,"image_slice_index":29,"page_id":334},{"image_slice_id":13909,"image_slice_original_path":"http:\/\/quran.kemenag.go.id\/api\/source\/slice\/4\/4_30.jpg","image_slice_original_width":175,"image_slice_original_height":100,"image_slice_large_path":"","image_slice_large_width":0,"image_slice_large_height":0,"image_slice_medium_path":"","image_slice_medium_width":0,"image_slice_medium_height":0,"image_slice_small_path":"","image_slice_small_width":0,"image_slice_small_height":0,"image_slice_thumbnail_path":"","image_slice_thumbnail_width":0,"image_slice_thumbnail_height":0,"aya_id":null,"image_slice_index":30,"page_id":334},{"image_slice_id":13910,"image_slice_original_path":"http:\/\/quran.kemenag.go.id\/api\/source\/slice\/4\/4_31.jpg","image_slice_original_width":176,"image_slice_original_height":198,"image_slice_large_path":"","image_slice_large_width":0,"image_slice_large_height":0,"image_slice_medium_path":"","image_slice_medium_width":0,"image_slice_medium_height":0,"image_slice_small_path":"","image_slice_small_width":0,"image_slice_small_height":0,"image_slice_thumbnail_path":"","image_slice_thumbnail_width":0,"image_slice_thumbnail_height":0,"aya_id":null,"image_slice_index":31,"page_id":334},{"image_slice_id":13911,"image_slice_original_path":"http:\/\/quran.kemenag.go.id\/api\/source\/slice\/4\/4_32.jpg","image_slice_original_width":999,"image_slice_original_height":198,"image_slice_large_path":"","image_slice_large_width":0,"image_slice_large_height":0,"image_slice_medium_path":"","image_slice_medium_width":0,"image_slice_medium_height":0,"image_slice_small_path":"","image_slice_small_width":0,"image_slice_small_height":0,"image_slice_thumbnail_path":"","image_slice_thumbnail_width":0,"image_slice_thumbnail_height":0,"aya_id":29,"image_slice_index":32,"page_id":334},{"image_slice_id":13912,"image_slice_original_path":"http:\/\/quran.kemenag.go.id\/api\/source\/slice\/4\/4_33.jpg","image_slice_original_width":175,"image_slice_original_height":198,"image_slice_large_path":"","image_slice_large_width":0,"image_slice_large_height":0,"image_slice_medium_path":"","image_slice_medium_width":0,"image_slice_medium_height":0,"image_slice_small_path":"","image_slice_small_width":0,"image_slice_small_height":0,"image_slice_thumbnail_path":"","image_slice_thumbnail_width":0,"image_slice_thumbnail_height":0,"aya_id":null,"image_slice_index":33,"page_id":334},{"image_slice_id":13913,"image_slice_original_path":"http:\/\/quran.kemenag.go.id\/api\/source\/slice\/4\/4_34.jpg","image_slice_original_width":176,"image_slice_original_height":104,"image_slice_large_path":"","image_slice_large_width":0,"image_slice_large_height":0,"image_slice_medium_path":"","image_slice_medium_width":0,"image_slice_medium_height":0,"image_slice_small_path":"","image_slice_small_width":0,"image_slice_small_height":0,"image_slice_thumbnail_path":"","image_slice_thumbnail_width":0,"image_slice_thumbnail_height":0,"aya_id":null,"image_slice_index":34,"page_id":334},{"image_slice_id":13914,"image_slice_original_path":"http:\/\/quran.kemenag.go.id\/api\/source\/slice\/4\/4_35.jpg","image_slice_original_width":694,"image_slice_original_height":104,"image_slice_large_path":"","image_slice_large_width":0,"image_slice_large_height":0,"image_slice_medium_path":"","image_slice_medium_width":0,"image_slice_medium_height":0,"image_slice_small_path":"","image_slice_small_width":0,"image_slice_small_height":0,"image_slice_thumbnail_path":"","image_slice_thumbnail_width":0,"image_slice_thumbnail_height":0,"aya_id":30,"image_slice_index":35,"page_id":334},{"image_slice_id":13915,"image_slice_original_path":"http:\/\/quran.kemenag.go.id\/api\/source\/slice\/4\/4_36.jpg","image_slice_original_width":305,"image_slice_original_height":104,"image_slice_large_path":"","image_slice_large_width":0,"image_slice_large_height":0,"image_slice_medium_path":"","image_slice_medium_width":0,"image_slice_medium_height":0,"image_slice_small_path":"","image_slice_small_width":0,"image_slice_small_height":0,"image_slice_thumbnail_path":"","image_slice_thumbnail_width":0,"image_slice_thumbnail_height":0,"aya_id":29,"image_slice_index":36,"page_id":334},{"image_slice_id":13916,"image_slice_original_path":"http:\/\/quran.kemenag.go.id\/api\/source\/slice\/4\/4_37.jpg","image_slice_original_width":175,"image_slice_original_height":104,"image_slice_large_path":"","image_slice_large_width":0,"image_slice_large_height":0,"image_slice_medium_path":"","image_slice_medium_width":0,"image_slice_medium_height":0,"image_slice_small_path":"","image_slice_small_width":0,"image_slice_small_height":0,"image_slice_thumbnail_path":"","image_slice_thumbnail_width":0,"image_slice_thumbnail_height":0,"aya_id":null,"image_slice_index":37,"page_id":334},{"image_slice_id":13917,"image_slice_original_path":"http:\/\/quran.kemenag.go.id\/api\/source\/slice\/4\/4_38.jpg","image_slice_original_width":176,"image_slice_original_height":102,"image_slice_large_path":"","image_slice_large_width":0,"image_slice_large_height":0,"image_slice_medium_path":"","image_slice_medium_width":0,"image_slice_medium_height":0,"image_slice_small_path":"","image_slice_small_width":0,"image_slice_small_height":0,"image_slice_thumbnail_path":"","image_slice_thumbnail_width":0,"image_slice_thumbnail_height":0,"aya_id":null,"image_slice_index":38,"page_id":334},{"image_slice_id":13918,"image_slice_original_path":"http:\/\/quran.kemenag.go.id\/api\/source\/slice\/4\/4_39.jpg","image_slice_original_width":999,"image_slice_original_height":102,"image_slice_large_path":"","image_slice_large_width":0,"image_slice_large_height":0,"image_slice_medium_path":"","image_slice_medium_width":0,"image_slice_medium_height":0,"image_slice_small_path":"","image_slice_small_width":0,"image_slice_small_height":0,"image_slice_thumbnail_path":"","image_slice_thumbnail_width":0,"image_slice_thumbnail_height":0,"aya_id":30,"image_slice_index":39,"page_id":334},{"image_slice_id":13919,"image_slice_original_path":"http:\/\/quran.kemenag.go.id\/api\/source\/slice\/4\/4_40.jpg","image_slice_original_width":175,"image_slice_original_height":102,"image_slice_large_path":"","image_slice_large_width":0,"image_slice_large_height":0,"image_slice_medium_path":"","image_slice_medium_width":0,"image_slice_medium_height":0,"image_slice_small_path":"","image_slice_small_width":0,"image_slice_small_height":0,"image_slice_thumbnail_path":"","image_slice_thumbnail_width":0,"image_slice_thumbnail_height":0,"aya_id":null,"image_slice_index":40,"page_id":334},{"image_slice_id":13920,"image_slice_original_path":"http:\/\/quran.kemenag.go.id\/api\/source\/slice\/4\/4_41.jpg","image_slice_original_width":176,"image_slice_original_height":91,"image_slice_large_path":"","image_slice_large_width":0,"image_slice_large_height":0,"image_slice_medium_path":"","image_slice_medium_width":0,"image_slice_medium_height":0,"image_slice_small_path":"","image_slice_small_width":0,"image_slice_small_height":0,"image_slice_thumbnail_path":"","image_slice_thumbnail_width":0,"image_slice_thumbnail_height":0,"aya_id":null,"image_slice_index":41,"page_id":334},{"image_slice_id":13921,"image_slice_original_path":"http:\/\/quran.kemenag.go.id\/api\/source\/slice\/4\/4_42.jpg","image_slice_original_width":615,"image_slice_original_height":91,"image_slice_large_path":"","image_slice_large_width":0,"image_slice_large_height":0,"image_slice_medium_path":"","image_slice_medium_width":0,"image_slice_medium_height":0,"image_slice_small_path":"","image_slice_small_width":0,"image_slice_small_height":0,"image_slice_thumbnail_path":"","image_slice_thumbnail_width":0,"image_slice_thumbnail_height":0,"aya_id":31,"image_slice_index":42,"page_id":334},{"image_slice_id":13922,"image_slice_original_path":"http:\/\/quran.kemenag.go.id\/api\/source\/slice\/4\/4_43.jpg","image_slice_original_width":384,"image_slice_original_height":91,"image_slice_large_path":"","image_slice_large_width":0,"image_slice_large_height":0,"image_slice_medium_path":"","image_slice_medium_width":0,"image_slice_medium_height":0,"image_slice_small_path":"","image_slice_small_width":0,"image_slice_small_height":0,"image_slice_thumbnail_path":"","image_slice_thumbnail_width":0,"image_slice_thumbnail_height":0,"aya_id":30,"image_slice_index":43,"page_id":334},{"image_slice_id":13923,"image_slice_original_path":"http:\/\/quran.kemenag.go.id\/api\/source\/slice\/4\/4_44.jpg","image_slice_original_width":175,"image_slice_original_height":91,"image_slice_large_path":"","image_slice_large_width":0,"image_slice_large_height":0,"image_slice_medium_path":"","image_slice_medium_width":0,"image_slice_medium_height":0,"image_slice_small_path":"","image_slice_small_width":0,"image_slice_small_height":0,"image_slice_thumbnail_path":"","image_slice_thumbnail_width":0,"image_slice_thumbnail_height":0,"aya_id":null,"image_slice_index":44,"page_id":334},{"image_slice_id":13924,"image_slice_original_path":"http:\/\/quran.kemenag.go.id\/api\/source\/slice\/4\/4_45.jpg","image_slice_original_width":176,"image_slice_original_height":116,"image_slice_large_path":"","image_slice_large_width":0,"image_slice_large_height":0,"image_slice_medium_path":"","image_slice_medium_width":0,"image_slice_medium_height":0,"image_slice_small_path":"","image_slice_small_width":0,"image_slice_small_height":0,"image_slice_thumbnail_path":"","image_slice_thumbnail_width":0,"image_slice_thumbnail_height":0,"aya_id":null,"image_slice_index":45,"page_id":334},{"image_slice_id":13925,"image_slice_original_path":"http:\/\/quran.kemenag.go.id\/api\/source\/slice\/4\/4_46.jpg","image_slice_original_width":999,"image_slice_original_height":116,"image_slice_large_path":"","image_slice_large_width":0,"image_slice_large_height":0,"image_slice_medium_path":"","image_slice_medium_width":0,"image_slice_medium_height":0,"image_slice_small_path":"","image_slice_small_width":0,"image_slice_small_height":0,"image_slice_thumbnail_path":"","image_slice_thumbnail_width":0,"image_slice_thumbnail_height":0,"aya_id":31,"image_slice_index":46,"page_id":334},{"image_slice_id":13926,"image_slice_original_path":"http:\/\/quran.kemenag.go.id\/api\/source\/slice\/4\/4_47.jpg","image_slice_original_width":175,"image_slice_original_height":116,"image_slice_large_path":"","image_slice_large_width":0,"image_slice_large_height":0,"image_slice_medium_path":"","image_slice_medium_width":0,"image_slice_medium_height":0,"image_slice_small_path":"","image_slice_small_width":0,"image_slice_small_height":0,"image_slice_thumbnail_path":"","image_slice_thumbnail_width":0,"image_slice_thumbnail_height":0,"aya_id":null,"image_slice_index":47,"page_id":334},{"image_slice_id":13927,"image_slice_original_path":"http:\/\/quran.kemenag.go.id\/api\/source\/slice\/4\/4_48.jpg","image_slice_original_width":1350,"image_slice_original_height":172,"image_slice_large_path":"","image_slice_large_width":0,"image_slice_large_height":0,"image_slice_medium_path":"","image_slice_medium_width":0,"image_slice_medium_height":0,"image_slice_small_path":"","image_slice_small_width":0,"image_slice_small_height":0,"image_slice_thumbnail_path":"","image_slice_thumbnail_width":0,"image_slice_thumbnail_height":0,"aya_id":null,"image_slice_index":48,"page_id":334}]}
